pandemsource/__init__.py
pandemsource/__main__.py
pandemsource/acquisition.py
pandemsource/acquisition_git.py
pandemsource/acquisition_git_local.py
pandemsource/acquisition_localFS.py
pandemsource/acquisition_medisys.py
pandemsource/acquisition_twitter.py
pandemsource/acquisition_url.py
pandemsource/acquisition_zenodo.py
pandemsource/admin.py
pandemsource/aggregator.py
pandemsource/api.py
pandemsource/config.py
pandemsource/dfreader.py
pandemsource/evaluator.py
pandemsource/formatreader.py
pandemsource/formatreader_csv.py
pandemsource/formatreader_json.py
pandemsource/formatreader_xls.py
pandemsource/formatreader_xml.py
pandemsource/nlp_annotator.py
pandemsource/orchestrator.py
pandemsource/pipeline.py
pandemsource/script_executor.py
pandemsource/standardizer.py
pandemsource/storage.py
pandemsource/unarchive.py
pandemsource/util.py
pandemsource/variables.py
pandemsource/worker.py
pandemsource/data/.defaults.yml.swp
pandemsource/data/.~lock.list-of-variables.csv#
pandemsource/data/defaults.yml
pandemsource/data/list-of-variables.csv
pandemsource/data/variables-summary.csv
pandemsource/data/DLS/ICD-10-diseases-list.json
pandemsource/data/DLS/ICD-10-diseases.json
pandemsource/data/DLS/covid19-datahub-AUT.json
pandemsource/data/DLS/covid19-datahub-BEL.json
pandemsource/data/DLS/covid19-datahub-BGR.json
pandemsource/data/DLS/covid19-datahub-CYP.json
pandemsource/data/DLS/covid19-datahub-CZE.json
pandemsource/data/DLS/covid19-datahub-DEU.json
pandemsource/data/DLS/covid19-datahub-DNK.json
pandemsource/data/DLS/covid19-datahub-ESP.json
pandemsource/data/DLS/covid19-datahub-EST.json
pandemsource/data/DLS/covid19-datahub-FIN.json
pandemsource/data/DLS/covid19-datahub-FRA.json
pandemsource/data/DLS/covid19-datahub-GBR.json
pandemsource/data/DLS/covid19-datahub-GRC.json
pandemsource/data/DLS/covid19-datahub-HRV.json
pandemsource/data/DLS/covid19-datahub-HUN.json
pandemsource/data/DLS/covid19-datahub-IRL.json
pandemsource/data/DLS/covid19-datahub-ITA.json
pandem_source-1.1.7.dist-info/LICENCE
pandem_source-1.1.7.dist-info/METADATA
pandem_source-1.1.7.dist-info/WHEEL
pandem_source-1.1.7.dist-info/top_level.txt
pandem_source-1.1.7.dist-info/RECORD
