Metadata-Version: 2.1
Name: pandem-source
Version: 1.1.7
Summary: Routinely collecting heterogeneous surveillance data into a coherent database
Home-page: https://github.com/pandem2/pandem-source
Author: Francisco Orchard
Author-email: f.orchard@epiconcept.fr
License: EUPL-1.2
License-File: LICENCE
Requires-Dist: pyyaml
Requires-Dist: pandas
Requires-Dist: openpyxl
Requires-Dist: pykka
Requires-Dist: psutil
Requires-Dist: lxml
Requires-Dist: isoweek
Requires-Dist: tweepy
Requires-Dist: tornado
Requires-Dist: asyncio
Requires-Dist: tornado-rest-swagger
